OTVision/__init__.py
OTVision/config.py
OTVision/dataformat.py
OTVision/version.py
OTVision/abstraction/__init__.py
OTVision/abstraction/defaults.py
OTVision/abstraction/observer.py
OTVision/abstraction/pipes_and_filter.py
OTVision/application/__init__.py
OTVision/application/buffer.py
OTVision/application/config.py
OTVision/application/config_parser.py
OTVision/application/configure_logger.py
OTVision/application/frame_count_provider.py
OTVision/application/get_config.py
OTVision/application/get_current_config.py
OTVision/application/otvision_save_path_provider.py
OTVision/application/update_current_config.py
OTVision/application/detect/__init__.py
OTVision/application/detect/current_object_detector.py
OTVision/application/detect/current_object_detector_metadata.py
OTVision/application/detect/detected_frame_factory.py
OTVision/application/detect/factory.py
OTVision/application/detect/get_detect_cli_args.py
OTVision/application/detect/timestamper.py
OTVision/application/detect/update_detect_config_with_cli_args.py
OTVision/application/event/__init__.py
OTVision/application/event/new_otvision_config.py
OTVision/application/event/new_video_start.py
OTVision/application/track/__init__.py
OTVision/application/track/get_track_cli_args.py
OTVision/application/track/ottrk.py
OTVision/application/track/tracking_run_id.py
OTVision/application/track/update_current_track_config.py
OTVision/application/track/update_track_config_with_cli_args.py
OTVision/application/video/__init__.py
OTVision/application/video/generate_video.py
OTVision/convert/__init__.py
OTVision/convert/convert.py
OTVision/detect/__init__.py
OTVision/detect/builder.py
OTVision/detect/cli.py
OTVision/detect/detect.py
OTVision/detect/detected_frame_buffer.py
OTVision/detect/detected_frame_producer.py
OTVision/detect/detected_frame_producer_factory.py
OTVision/detect/file_based_detect_builder.py
OTVision/detect/otdet.py
OTVision/detect/otdet_file_writer.py
OTVision/detect/pyav_frame_count_provider.py
otvision-0.6.17.dist-info/METADATA
otvision-0.6.17.dist-info/WHEEL
otvision-0.6.17.dist-info/licenses/LICENSE
otvision-0.6.17.dist-info/RECORD
