Metadata-Version: 2.4
Name: OTVision
Version: 0.6.17
Summary: OTVision is a core module of the OpenTrafficCam framework to perform object detection and tracking.
Project-URL: Homepage, https://opentrafficcam.org/
Project-URL: Documentation, https://opentrafficcam.org/overview/
Project-URL: Repository, https://github.com/OpenTrafficCam/OTVision
Project-URL: Issues, https://github.com/OpenTrafficCam/OTVision/issues
Project-URL: Changelog, https://github.com/OpenTrafficCam/OTVision/releases
Author-email: OpenTrafficCam contributors <team@opentrafficcam.org>, platomo GmbH <info@platomo.de>
License-Expression: GPL-3.0-only
License-File: LICENSE
Keywords: OpenTrafficCam,Traffic Analysis,Traffic Counting,Trajectories
Classifier: Development Status :: 4 - Beta
Classifier: License :: OSI Approved :: GNU General Public License v3 (GPLv3)
Classifier: Operating System :: OS Independent
Classifier: Programming Language :: Python :: 3
Requires-Python: ==3.12.*
Requires-Dist: av==13.0.0
Requires-Dist: coremltools==8.2; sys_platform == 'darwin'
Requires-Dist: ffmpeg-python==0.2.0
Requires-Dist: fire==0.7.0
Requires-Dist: geopandas==1.0.1
Requires-Dist: ijson==3.3.0
Requires-Dist: more-itertools==10.7.0
Requires-Dist: moviepy==1.0.3
Requires-Dist: numpy==1.26.4; sys_platform == 'win32'
Requires-Dist: numpy==2.1.1; sys_platform != 'win32'
Requires-Dist: opencv-python-headless==4.10.0.84
Requires-Dist: pandas==2.3.3
Requires-Dist: pyyaml==6.0.2
Requires-Dist: tqdm==4.67.1
Requires-Dist: ujson==5.10.0
Provides-Extra: inference-cpu
Requires-Dist: torch==2.7.1; extra == 'inference-cpu'
Requires-Dist: torchvision==0.22.1; extra == 'inference-cpu'
Requires-Dist: ultralytics==8.3.159; extra == 'inference-cpu'
Provides-Extra: inference-cuda
Requires-Dist: tensorrt-cu12-bindings==10.12.0.36; (sys_platform != 'darwin') and extra == 'inference-cuda'
Requires-Dist: tensorrt-cu12-libs==10.12.0.36; (sys_platform != 'darwin') and extra == 'inference-cuda'
Requires-Dist: tensorrt==10.12.0.36; (sys_platform != 'darwin') and extra == 'inference-cuda'
Requires-Dist: torch==2.7.1; extra == 'inference-cuda'
Requires-Dist: torchvision==0.22.1; extra == 'inference-cuda'
Requires-Dist: ultralytics==8.3.159; extra == 'inference-cuda'
